asterx_utils/__init__.py
asterx_utils/__version__.py
asterx_utils/config.py
asterx_utils/auth/__init__.py
asterx_utils/auth/google_iap/__init__.py
asterx_utils/auth/google_iap/validate_jwt.py
asterx_utils/file/__init__.py
asterx_utils/file/writer.py
asterx_utils-0.0.3.dist-info/METADATA
asterx_utils-0.0.3.dist-info/WHEEL
asterx_utils-0.0.3.dist-info/top_level.txt
asterx_utils-0.0.3.dist-info/RECORD
